chemspyd/__init__.py
chemspyd/controller.py
chemspyd/exceptions.py
chemspyd/executor.py
chemspyd/py.typed
chemspyd/autosuite/__init__.py
chemspyd/autosuite/read_app.py
chemspyd/autosuite/utils.py
chemspyd/routines/__init__.py
chemspyd/routines/routines.py
chemspyd/utils/__init__.py
chemspyd/utils/csv_handling.py
chemspyd/utils/json_handling.py
chemspyd/utils/logging_utils.py
chemspyd/utils/precision.py
chemspyd/utils/unit_conversions.py
chemspyd/utils/well_monitoring.py
chemspyd/zones/__init__.py
chemspyd/zones/chemspeed_element.py
chemspyd/zones/chemspeed_well.py
chemspyd/zones/well_group.py
chemspyd/zones/zone_utils.py
chemspyd-1.0.0.dist-info/LICENSE
chemspyd-1.0.0.dist-info/METADATA
chemspyd-1.0.0.dist-info/WHEEL
chemspyd-1.0.0.dist-info/top_level.txt
chemspyd-1.0.0.dist-info/RECORD
