Metadata-Version: 2.1
Name: chemspyd
Version: 1.0.0
Summary: A Python API for the Chemspeed AutoSuite software.
Author-email: Martin Seifrid <m.seifrid@utoronto.ca>, Felix Strieth-Kalthoff <f.striethkalthoff@utoronto.ca>, Mohammad Haddadnia <m.nia@mail.utoronto.ca>, "Tony C. Wu" <tonyc.wu@utoronto.ca>, Emre Alca <emre.alca@mail.utoronto.ca>
Maintainer-email: Martin Seifrid <m.seifrid@utoronto.ca>, Felix Strieth-Kalthoff <f.striethkalthoff@utoronto.ca>, Mohammad Haddadnia <m.nia@mail.utoronto.ca>
License: Apache License
Project-URL: Homepage, https://aspuru-guzik-group.gitlab.io/self-driving-lab/instruments/chemspyd/
Project-URL: Repository, https://gitlab.com/aspuru-guzik-group/self-driving-lab/instruments/chemspyd/
Project-URL: Bug Tracker, https://gitlab.com/aspuru-guzik-group/self-driving-lab/instruments/chemspyd/-/issues
Keywords: chemistry,automation,chemspeed,synthesis,self-driving labs
Classifier: License :: OSI Approved :: Apache Software License
Classifier: Programming Language :: Python
Classifier: Programming Language :: Python :: 3
Classifier: Programming Language :: Python :: 3 :: Only
Classifier: Programming Language :: Python :: 3.9
Classifier: Programming Language :: Python :: 3.10
Classifier: Programming Language :: Python :: 3.11
Classifier: Programming Language :: Python :: 3.12
Classifier: Intended Audience :: Science/Research
Classifier: Topic :: Software Development
Classifier: Topic :: Scientific/Engineering
Classifier: Topic :: Scientific/Engineering :: Chemistry
Requires-Python: >=3.9
License-File: LICENSE
Requires-Dist: setuptools
Requires-Dist: deprecation
Requires-Dist: scipy
Provides-Extra: dev
Requires-Dist: black ; extra == 'dev'
Requires-Dist: flake8 ; extra == 'dev'
Requires-Dist: mypy ; extra == 'dev'
Requires-Dist: pytest ; extra == 'dev'
Requires-Dist: pytest-cov ; extra == 'dev'
Requires-Dist: pytest-timeout ; extra == 'dev'
Requires-Dist: pytest-rerunfailures ; extra == 'dev'
Requires-Dist: hypothesis ; extra == 'dev'
Requires-Dist: flake8-pyproject ; extra == 'dev'
